pyridis_api-0.3.5.dist-info/METADATA
pyridis_api-0.3.5.dist-info/WHEEL
pyridis_api/__init__.py
pyridis_api/__init__.pyi
pyridis_api/pyridis_api.cpython-313t-i386-linux-gnu.so
pyridis_api-0.3.5.dist-info/RECORD
